[
  {
    "time": 0,
    "gold": 0,
    "wood": 0,
    "food": 5,
    "foodMax": 12,
    "action": "4 Workler Mine + 1 to Wood then train 2 worker",
    "icons": [
      "Peasant",
      "Peasant",
      "Peasant",
      "Peasant",
      "Arrow Right",
      "Gold Mine",
      "Spacer",
      "Peasant",
      "Arrow Right",
      "Wood"
    ],
    "useSound": false,
    "sound": "warcraft/aaaaahhhh.mp3",
    "hasPlayedSound": false
  },
  {
    "time": 15,
    "gold": 0,
    "wood": 0,
    "food": 7,
    "foodMax": 12,
    "action": "1. new worker -> Altar",
    "icons": [
      "Altar of Kings"
    ],
    "useSound": false,
    "sound": "warcraft/aaaaahhhh.mp3",
    "hasPlayedSound": false
  },
  {
    "time": 30,
    "gold": 0,
    "wood": 0,
    "food": 7,
    "foodMax": 12,
    "action": "2. new Worker -> Blacksmith",
    "icons": [
      "Blacksmith"
    ],
    "useSound": false,
    "sound": "warcraft/aaaaahhhh.mp3",
    "hasPlayedSound": false
  },
  {
    "time": 45,
    "gold": 0,
    "wood": 0,
    "food": 8,
    "foodMax": 12,
    "action": "3. new Worker -> Barracks then send ALTAR building Worker -> build Farm",
    "icons": [
      "Peasant",
      "Arrow Right",
      "Barracks",
      "Spacer",
      "Altar of Kings",
      "Peasant",
      "Arrow Right",
      "Farm"
    ],
    "useSound": false,
    "sound": "warcraft/aaaaahhhh.mp3",
    "hasPlayedSound": false
  },
  {
    "time": 60,
    "gold": 0,
    "wood": 0,
    "food": 9,
    "foodMax": 12,
    "action": "4. new Worker continues to build Altar",
    "icons": [
      "Peasant",
      "Arrow Right",
      "Altar of Kings"
    ],
    "useSound": false,
    "sound": "warcraft/aaaaahhhh.mp3",
    "hasPlayedSound": false
  },
  {
    "time": 75,
    "gold": 0,
    "wood": 0,
    "food": 10,
    "foodMax": 12,
    "action": "5. new Worker -> 2. Farm",
    "icons": [
      "Peasant",
      "Arrow Right",
      "Farm"
    ],
    "useSound": false,
    "sound": "warcraft/aaaaahhhh.mp3",
    "hasPlayedSound": false
  },
  {
    "time": 80,
    "gold": 0,
    "wood": 0,
    "food": 10,
    "foodMax": 12,
    "action": "PRE send building worker to Wood",
    "icons": [
      "Peasant",
      "Wood"
    ],
    "useSound": false,
    "sound": "warcraft/aaaaahhhh.mp3",
    "hasPlayedSound": false
  },
  {
    "time": 90,
    "gold": 0,
    "wood": 0,
    "food": 11,
    "foodMax": 12,
    "action": "6. new Worker -> Gold",
    "icons": [
      "Peasant",
      "Arrow Right",
      "Gold Mine"
    ],
    "useSound": false,
    "sound": "warcraft/aaaaahhhh.mp3",
    "hasPlayedSound": false
  },
  {
    "time": 95,
    "gold": 0,
    "wood": 0,
    "food": 12,
    "foodMax": 18,
    "action": "train Pala",
    "icons": [
      "Paladin"
    ],
    "useSound": true,
    "sound": "voice/train hero.mp3",
    "hasPlayedSound": false
  },
  {
    "time": 105,
    "gold": 0,
    "wood": 0,
    "food": 18,
    "foodMax": 24,
    "action": "train 1. Rifle",
    "icons": [
      "Rifleman"
    ],
    "useSound": false,
    "sound": "warcraft/aaaaahhhh.mp3",
    "hasPlayedSound": false
  },
  {
    "time": 110,
    "gold": 0,
    "wood": 0,
    "food": 21,
    "foodMax": 24,
    "action": "PRE Group 3-4 Peasants",
    "icons": [
      "Peasant",
      "Peasant",
      "Peasant",
      "Spacer",
      "Peasant"
    ],
    "useSound": true,
    "sound": "voice/fix army.mp3",
    "hasPlayedSound": false
  },
  {
    "time": 120,
    "gold": 0,
    "wood": 0,
    "food": 21,
    "foodMax": 24,
    "action": "last worker -> 3. Farm",
    "icons": [
      "Peasant",
      "Arrow Right",
      "Farm"
    ],
    "useSound": false,
    "sound": "warcraft/aaaaahhhh.mp3",
    "hasPlayedSound": false
  },
  {
    "time": 140,
    "gold": 0,
    "wood": 0,
    "food": 21,
    "foodMax": 24,
    "action": "train 2. Rifle",
    "icons": [
      "Rifleman"
    ],
    "useSound": false,
    "sound": "warcraft/aaaaahhhh.mp3",
    "hasPlayedSound": false
  },
  {
    "time": 150,
    "gold": 0,
    "wood": 0,
    "food": 24,
    "foodMax": 24,
    "action": "Start creeping Orange camp",
    "icons": [
      "Paladin",
      "Rifleman",
      "Militia",
      "Militia",
      "Militia",
      "Militia"
    ],
    "useSound": true,
    "sound": "voice/creep.mp3",
    "hasPlayedSound": false
  },
  {
    "time": 175,
    "gold": 0,
    "wood": 0,
    "food": 27,
    "foodMax": 30,
    "action": "train 3. Rifle",
    "icons": [
      "Rifleman"
    ],
    "useSound": true,
    "sound": "voice/train units.mp3",
    "hasPlayedSound": false
  },
  {
    "time": 195,
    "gold": 0,
    "wood": 0,
    "food": 27,
    "foodMax": 30,
    "action": "either train 4. rifle OR tech 2",
    "icons": [
      "Rifleman",
      "Spacer",
      "Keep"
    ],
    "useSound": true,
    "sound": "voice/tech 2.mp3",
    "hasPlayedSound": false
  },
  {
    "time": 205,
    "gold": 0,
    "wood": 0,
    "food": 0,
    "foodMax": 0,
    "action": "remember to Creep",
    "icons": [
      "Ogre Mauler"
    ],
    "useSound": true,
    "sound": "voice/creep.mp3",
    "hasPlayedSound": false
  },
  {
    "time": 220,
    "gold": 0,
    "wood": 0,
    "food": 27,
    "foodMax": 30,
    "action": "either tech 2 /4. rifle or build farm",
    "icons": [
      "Keep",
      "Rifleman",
      "Spacer",
      "Farm"
    ],
    "useSound": true,
    "sound": "voice/base.mp3",
    "hasPlayedSound": false
  },
  {
    "time": 305,
    "gold": 0,
    "wood": 0,
    "food": 33,
    "foodMax": 36,
    "action": "5. Farm",
    "icons": [
      "Farm"
    ],
    "useSound": true,
    "sound": "voice/base.mp3",
    "hasPlayedSound": false
  },
  {
    "time": 335,
    "gold": 0,
    "wood": 0,
    "food": 33,
    "foodMax": 36,
    "action": "5. Rifle",
    "icons": [
      "Rifleman"
    ],
    "useSound": false,
    "sound": "warcraft/aaaaahhhh.mp3",
    "hasPlayedSound": false
  },
  {
    "time": 360,
    "gold": 0,
    "wood": 0,
    "food": 36,
    "foodMax": 36,
    "action": "6. Rifle and continue producing",
    "icons": [
      "Rifleman"
    ],
    "useSound": false,
    "sound": "warcraft/aaaaahhhh.mp3",
    "hasPlayedSound": false
  },
  {
    "time": 415,
    "gold": 0,
    "wood": 0,
    "food": 36,
    "foodMax": 44,
    "action": "BM + Sanctum",
    "icons": [
      "Blood Mage",
      "Arcane Sanctum"
    ],
    "useSound": true,
    "sound": "voice/train hero.mp3",
    "hasPlayedSound": false
  },
  {
    "time": 450,
    "gold": 0,
    "wood": 0,
    "food": 42,
    "foodMax": 44,
    "action": "6. Farm",
    "icons": [
      "Farm"
    ],
    "useSound": false,
    "sound": "warcraft/aaaaahhhh.mp3",
    "hasPlayedSound": false
  },
  {
    "time": 485,
    "gold": 0,
    "wood": 0,
    "food": 44,
    "foodMax": 50,
    "action": "upgrade Long Rifles, train Priest",
    "icons": [
      "Long Rifles",
      "Priest"
    ],
    "useSound": true,
    "sound": "voice/base.mp3",
    "hasPlayedSound": false
  },
  {
    "time": 515,
    "gold": 0,
    "wood": 0,
    "food": 0,
    "foodMax": 0,
    "action": "build Shop -> attack",
    "icons": [
      "Arcane Vault",
      "Arrow Right"
    ],
    "useSound": true,
    "sound": "voice/base.mp3",
    "hasPlayedSound": false
  }
]